sportbooking/__init__.py
sportbooking/login.py
sportbooking/py.typed
sportbooking/reservation_calendar.py
sportbooking/reservation_query_input.py
sportbooking/user_account_info.py
sportbooking/_internal/__init__.py
sportbooking/_internal/common.py
sportbooking/_internal/login.py
sportbooking/_internal/reservation_input.py
sportbooking/_internal/reserve.py
sportbooking/_internal/user_account.py
sportbooking/_internal/reservation_calendar/__init__.py
sportbooking/_internal/reservation_calendar/reservation_calendar.py
sportbooking/_internal/reservation_calendar/reservation_calendar_html_parser.py
sportbooking-0.1.0.dist-info/METADATA
sportbooking-0.1.0.dist-info/WHEEL
sportbooking-0.1.0.dist-info/RECORD
