Metadata-Version: 2.4
Name: sportbooking
Version: 0.1.0
Summary: Add your description here
Author-email: Ivo Petkovic <ivo.petkovic@gmail.com>
Requires-Python: >=3.12
Requires-Dist: bs4>=0.0.2
Requires-Dist: httpx>=0.28.1
Requires-Dist: pydantic>=2.11.7
